<?xml version="1.0"?>
<Checkpoint Version="4" Minor="0">
	<BUILD_NUMBER Name="1368829"/>
	<FULL_BUILD Name="SW Build 1368829 on Mon Sep 28 20:06:43 MDT 2015"/>
	<PRODUCT Name="Vivado v2015.3 (64-bit)"/>
	<Part Name="xc7a35tcpg236-1"/>
	<Top Name="display_top"/>
	<DisableAutoIOBuffers Name="0"/>
	<OutOfContext Name="0"/>
	<File Type="XDC" Name="display_top.xdc" ModTime="1511022304"/>
	<File Type="SHAPE" Name="display_top.shape" ModTime="1511022304"/>
	<File Type="EDIF" Name="display_top.edf" ModTime="1511022304"/>
	<File Type="VERILOG_STUB" Name="display_top_stub.v" ModTime="1511022304"/>
	<File Type="VHDL_STUB" Name="display_top_stub.vhdl" ModTime="1511022304"/>
	<File Type="XN" Name="display_top.xn" ModTime="1511022304"/>
	<File Type="XDEF" Name="display_top.xdef" ModTime="1511022304"/>
	<File Type="INCR" Name="display_top.incr" ModTime="1511022304"/>
	<File Type="REPLAY" Name="display_top_iPhysOpt.tcl" ModTime="1511022304"/>
	<File Type="PSR" Name="display_top.psr" ModTime="1511022304"/>
	<File Type="WDF" Name="display_top.wdf" ModTime="1511022304"/>
</Checkpoint>

